odoo/addons/mgmtsystem_survey/README.rst
odoo/addons/mgmtsystem_survey/__init__.py
odoo/addons/mgmtsystem_survey/__manifest__.py
odoo/addons/mgmtsystem_survey/i18n/de.po
odoo/addons/mgmtsystem_survey/i18n/es.po
odoo/addons/mgmtsystem_survey/i18n/es_CO.po
odoo/addons/mgmtsystem_survey/i18n/fi.po
odoo/addons/mgmtsystem_survey/i18n/fr.po
odoo/addons/mgmtsystem_survey/i18n/hr_HR.po
odoo/addons/mgmtsystem_survey/i18n/hu.po
odoo/addons/mgmtsystem_survey/i18n/it.po
odoo/addons/mgmtsystem_survey/i18n/lv.po
odoo/addons/mgmtsystem_survey/i18n/mgmtsystem_survey.pot
odoo/addons/mgmtsystem_survey/i18n/nb.po
odoo/addons/mgmtsystem_survey/i18n/nn.po
odoo/addons/mgmtsystem_survey/i18n/pt.po
odoo/addons/mgmtsystem_survey/i18n/pt_BR.po
odoo/addons/mgmtsystem_survey/i18n/sl.po
odoo/addons/mgmtsystem_survey/i18n/sv.po
odoo/addons/mgmtsystem_survey/i18n/th.po
odoo/addons/mgmtsystem_survey/i18n/tr.po
odoo/addons/mgmtsystem_survey/i18n/vi.po
odoo/addons/mgmtsystem_survey/migrations/13.0.1.0.0/pre-migration.py
odoo/addons/mgmtsystem_survey/models/__init__.py
odoo/addons/mgmtsystem_survey/models/survey_survey.py
odoo/addons/mgmtsystem_survey/readme/CONFIGURE.rst
odoo/addons/mgmtsystem_survey/readme/CONTRIBUTORS.rst
odoo/addons/mgmtsystem_survey/readme/DESCRIPTION.rst
odoo/addons/mgmtsystem_survey/readme/USAGE.rst
odoo/addons/mgmtsystem_survey/static/description/icon.png
odoo/addons/mgmtsystem_survey/static/description/index.html
odoo/addons/mgmtsystem_survey/views/survey_survey.xml
odoo13_addon_mgmtsystem_survey-13.0.1.0.1.dev9.dist-info/METADATA
odoo13_addon_mgmtsystem_survey-13.0.1.0.1.dev9.dist-info/WHEEL
odoo13_addon_mgmtsystem_survey-13.0.1.0.1.dev9.dist-info/top_level.txt
odoo13_addon_mgmtsystem_survey-13.0.1.0.1.dev9.dist-info/RECORD
